androidscan/__init__.py
androidscan/cli.py
androidscan-0.1.3.dist-info/licenses/LICENSE
androidscan-0.1.3.dist-info/METADATA
androidscan-0.1.3.dist-info/WHEEL
androidscan-0.1.3.dist-info/entry_points.txt
androidscan-0.1.3.dist-info/top_level.txt
androidscan-0.1.3.dist-info/RECORD
