Metadata-Version: 2.4
Name: androidscan
Version: 0.1.3
Summary: A simple android vuln cli scanner
Home-page: https://github.com/edoggy777/androidscan
Author: Evan Kirtz
Author-email: kirtzevan@gmail.com
License: MIT
Classifier: Programming Language :: Python :: 3
Classifier: License :: OSI Approved :: MIT License
Classifier: Operating System :: OS Independent
Requires-Python: >=3.8
License-File: LICENSE
Dynamic: license-file
